epiworldpy/__init__.py
epiworldpy/_core.cpython-312-darwin.so
epiworldpy-0.0.4.dist-info/METADATA
epiworldpy-0.0.4.dist-info/WHEEL
epiworldpy-0.0.4.dist-info/licenses/LICENSE
epiworldpy-0.0.4.dist-info/RECORD
