Metadata-Version: 2.1
Name: epiworldpy
Version: 0.0.4
Summary: Python bindings for epiworld
Author-Email: "George G. Vega Yon" <g.vegayon@gmail.com>, Milo Banks <milobanks@rowlandhall.org>
Classifier: Development Status :: 4 - Beta
Classifier: License :: OSI Approved :: MIT License
Classifier: Programming Language :: Python :: 3 :: Only
Classifier: Programming Language :: Python :: 3.7
Classifier: Programming Language :: Python :: 3.8
Classifier: Programming Language :: Python :: 3.9
Classifier: Programming Language :: Python :: 3.10
Classifier: Programming Language :: Python :: 3.11
Requires-Python: >=3.7
Requires-Dist: numpy
Requires-Dist: pytest; extra == "test"
Requires-Dist: nbformat; extra == "doc"
Requires-Dist: nbclient; extra == "doc"
Requires-Dist: jupyter; extra == "doc"
Requires-Dist: epiworldpy[viz]; extra == "doc"
Requires-Dist: myst_parser; extra == "doc"
Requires-Dist: ipympl>=0.8; extra == "viz"
Requires-Dist: matplotlib>=3.5.0; extra == "viz"
Requires-Dist: networkx>=3.0; extra == "viz"
Requires-Dist: scipy>=1.0; extra == "viz"
Provides-Extra: test
Provides-Extra: doc
Provides-Extra: viz
